{
    "instaloader": {
        "node_type": "Post",
        "version": "4.7.5"
    },
    "node": {
        "__typename": "GraphSidecar",
        "accessibility_caption": "Photo by Luca_bw_ on July 25, 2021. May be a closeup of 1 person.",
        "caption_is_edited": true,
        "commenting_disabled_for_viewer": false,
        "comments_disabled": false,
        "dimensions": {
            "height": 1350,
            "width": 1080
        },
        "display_resources": [
            {
                "config_height": 800,
                "config_width": 640,
                "src": "https://instagram.fsin7-1.fna.fbcdn.net/v/t51.2885-15/sh0.08/e35/p640x640/225063305_781609129200776_1169706515093739938_n.jpg?_nc_ht=instagram.fsin7-1.fna.fbcdn.net&_nc_cat=108&_nc_ohc=Gnfs6Ye08Y4AX8aHH-J&edm=AP_V10EBAAAA&ccb=7-4&oh=8560f0e7f4e50256dcfbc3581a53f68f&oe=6105530C&_nc_sid=4f375e"
            },
            {
                "config_height": 937,
                "config_width": 750,
                "src": "https://instagram.fsin7-1.fna.fbcdn.net/v/t51.2885-15/sh0.08/e35/p750x750/225063305_781609129200776_1169706515093739938_n.jpg?_nc_ht=instagram.fsin7-1.fna.fbcdn.net&_nc_cat=108&_nc_ohc=Gnfs6Ye08Y4AX8aHH-J&edm=AP_V10EBAAAA&ccb=7-4&oh=24514814b0c142ad0b22d36da966d264&oe=6105F590&_nc_sid=4f375e"
            },
            {
                "config_height": 1350,
                "config_width": 1080,
                "src": "https://instagram.fsin7-1.fna.fbcdn.net/v/t51.2885-15/e35/p1080x1080/225063305_781609129200776_1169706515093739938_n.jpg?_nc_ht=instagram.fsin7-1.fna.fbcdn.net&_nc_cat=108&_nc_ohc=Gnfs6Ye08Y4AX8aHH-J&edm=AP_V10EBAAAA&ccb=7-4&oh=07c34b8a7cfd0825180ffc56d1e8bb46&oe=6105AE8F&_nc_sid=4f375e"
            }
        ],
        "display_url": "https://instagram.fsin7-1.fna.fbcdn.net/v/t51.2885-15/e35/p1080x1080/225063305_781609129200776_1169706515093739938_n.jpg?_nc_ht=instagram.fsin7-1.fna.fbcdn.net&_nc_cat=108&_nc_ohc=Gnfs6Ye08Y4AX8aHH-J&edm=AP_V10EBAAAA&ccb=7-4&oh=07c34b8a7cfd0825180ffc56d1e8bb46&oe=6105AE8F&_nc_sid=4f375e",
        "edge_liked_by": {
            "count": 6
        },
        "edge_media_preview_like": {
            "count": 6,
            "edges": []
        },
        "edge_media_to_caption": {
            "edges": [
                {
                    "node": {
                        "text": "\ud83d\udca3\ud83d\udca3\ud83d\udca3\ud83d\udca5\ud83d\udca5\ud83d\udca5\ud83e\udde8\ud83e\udde8\ud83e\udde8 New Artwork by @marcorea.art #luca_bw_ #streetartglobe #streetartlover #streetartworldwide  #streetartporn #streetartgallery #streetartdaily #streetarts #streetartphoto #streetartglobe #streetartlover #streetartworldwide  #urbanart #sprayart  #artwork #graffiti #graffitiart #streetphotography #streetartroma #streetart #muralesart #stencil #laziocreativo #jj_urbanart #scattostreet"
                    }
                }
            ]
        },
        "edge_media_to_comment": {
            "count": 0,
            "edges": [],
            "page_info": {
                "end_cursor": null,
                "has_next_page": false
            }
        },
        "edge_media_to_sponsor_user": {
            "edges": []
        },
        "edge_media_to_tagged_user": {
            "edges": []
        },
        "edge_sidecar_to_children": {
            "edges": [
                {
                    "node": {
                        "__typename": "GraphImage",
                        "accessibility_caption": "Photo by Luca_bw_ on July 25, 2021. May be a closeup of 1 person.",
                        "dimensions": {
                            "height": 1350,
                            "width": 1080
                        },
                        "display_resources": [
                            {
                                "config_height": 800,
                                "config_width": 640,
                                "src": "https://instagram.fsin7-1.fna.fbcdn.net/v/t51.2885-15/sh0.08/e35/p640x640/225063305_781609129200776_1169706515093739938_n.jpg?_nc_ht=instagram.fsin7-1.fna.fbcdn.net&_nc_cat=108&_nc_ohc=Gnfs6Ye08Y4AX8aHH-J&edm=AP_V10EBAAAA&ccb=7-4&oh=8560f0e7f4e50256dcfbc3581a53f68f&oe=6105530C&_nc_sid=4f375e"
                            },
                            {
                                "config_height": 937,
                                "config_width": 750,
                                "src": "https://instagram.fsin7-1.fna.fbcdn.net/v/t51.2885-15/sh0.08/e35/p750x750/225063305_781609129200776_1169706515093739938_n.jpg?_nc_ht=instagram.fsin7-1.fna.fbcdn.net&_nc_cat=108&_nc_ohc=Gnfs6Ye08Y4AX8aHH-J&edm=AP_V10EBAAAA&ccb=7-4&oh=24514814b0c142ad0b22d36da966d264&oe=6105F590&_nc_sid=4f375e"
                            },
                            {
                                "config_height": 1350,
                                "config_width": 1080,
                                "src": "https://instagram.fsin7-1.fna.fbcdn.net/v/t51.2885-15/e35/p1080x1080/225063305_781609129200776_1169706515093739938_n.jpg?_nc_ht=instagram.fsin7-1.fna.fbcdn.net&_nc_cat=108&_nc_ohc=Gnfs6Ye08Y4AX8aHH-J&edm=AP_V10EBAAAA&ccb=7-4&oh=07c34b8a7cfd0825180ffc56d1e8bb46&oe=6105AE8F&_nc_sid=4f375e"
                            }
                        ],
                        "display_url": "https://instagram.fsin7-1.fna.fbcdn.net/v/t51.2885-15/e35/p1080x1080/225063305_781609129200776_1169706515093739938_n.jpg?_nc_ht=instagram.fsin7-1.fna.fbcdn.net&_nc_cat=108&_nc_ohc=Gnfs6Ye08Y4AX8aHH-J&edm=AP_V10EBAAAA&ccb=7-4&oh=07c34b8a7cfd0825180ffc56d1e8bb46&oe=6105AE8F&_nc_sid=4f375e",
                        "edge_media_to_tagged_user": {
                            "edges": []
                        },
                        "fact_check_information": null,
                        "fact_check_overall_rating": null,
                        "gating_info": null,
                        "id": "2626015606449954561",
                        "is_video": false,
                        "media_preview": "ACEq3RIIoQ7dFQE/lWHG91qDFlfyoz0HPIH06+5zV/UCRYnH91f6UWc/kxorKyrgAP1B/rg9qAIDa3dsN8b+YRyVOeR7ev6H0rTs7oXUYcDB6EehHUUstwIxkhj9BnHufQfWqmnqoeRkyFfa2D2Jz/8AroAo0UUUAadxH5loVOT8g6cnjBqo9jEUE6kj5QeDweOOM4FakP8Aq1/3R/KqDRmJDbwsA55Cnng9+eg7Hrz25oArQ232oks7Aqf4Tz68nJBxnr+VaNpAIS2CcEjr7f496qwefBGUYpvJAQcZOfXGB7jg+9aMEflIF6kdT6k8n9aAMKilooA2kkCIuf7o/lWXPbi6feTtPQHpwPTvk1fgHyg98CrEajHSgDPjsvK+cYdx93JJxj/P4VoRyB/Y9xVMqMscDOW5q9gcGgDAooooA//Z",
                        "shortcode": "CRxe0flFN8B",
                        "tracking_token": "eyJ2ZXJzaW9uIjo1LCJwYXlsb2FkIjp7ImlzX2FuYWx5dGljc190cmFja2VkIjpmYWxzZSwidXVpZCI6IjQ2ZmM4MmJhMTgwNTQyODg5MmQyODQzMWNkZjY0NzE1MjYyNjAxNTYwNjQ0OTk1NDU2MSJ9LCJzaWduYXR1cmUiOiIifQ=="
                    }
                },
                {
                    "node": {
                        "__typename": "GraphImage",
                        "accessibility_caption": "Photo by Luca_bw_ on July 25, 2021. May be art of 1 person and brick wall.",
                        "dimensions": {
                            "height": 1350,
                            "width": 1080
                        },
                        "display_resources": [
                            {
                                "config_height": 800,
                                "config_width": 640,
                                "src": "https://instagram.fsin7-1.fna.fbcdn.net/v/t51.2885-15/sh0.08/e35/p640x640/223122920_106911618257228_2164923458174983022_n.jpg?_nc_ht=instagram.fsin7-1.fna.fbcdn.net&_nc_cat=108&_nc_ohc=g9XjyMslh5EAX8q-jxR&edm=AP_V10EBAAAA&ccb=7-4&oh=7d683612d04844d8d9b51d345f8867dc&oe=610536DF&_nc_sid=4f375e"
                            },
                            {
                                "config_height": 937,
                                "config_width": 750,
                                "src": "https://instagram.fsin7-1.fna.fbcdn.net/v/t51.2885-15/sh0.08/e35/p750x750/223122920_106911618257228_2164923458174983022_n.jpg?_nc_ht=instagram.fsin7-1.fna.fbcdn.net&_nc_cat=108&_nc_ohc=g9XjyMslh5EAX8q-jxR&edm=AP_V10EBAAAA&ccb=7-4&oh=72d579fdb69fdbd1ba4a53f1e553181f&oe=6104AE9B&_nc_sid=4f375e"
                            },
                            {
                                "config_height": 1350,
                                "config_width": 1080,
                                "src": "https://instagram.fsin7-1.fna.fbcdn.net/v/t51.2885-15/e35/p1080x1080/223122920_106911618257228_2164923458174983022_n.jpg?_nc_ht=instagram.fsin7-1.fna.fbcdn.net&_nc_cat=108&_nc_ohc=g9XjyMslh5EAX8q-jxR&edm=AP_V10EBAAAA&ccb=7-4&oh=534d97836cf7723902226365811aaa63&oe=6104D5DC&_nc_sid=4f375e"
                            }
                        ],
                        "display_url": "https://instagram.fsin7-1.fna.fbcdn.net/v/t51.2885-15/e35/p1080x1080/223122920_106911618257228_2164923458174983022_n.jpg?_nc_ht=instagram.fsin7-1.fna.fbcdn.net&_nc_cat=108&_nc_ohc=g9XjyMslh5EAX8q-jxR&edm=AP_V10EBAAAA&ccb=7-4&oh=534d97836cf7723902226365811aaa63&oe=6104D5DC&_nc_sid=4f375e",
                        "edge_media_to_tagged_user": {
                            "edges": []
                        },
                        "fact_check_information": null,
                        "fact_check_overall_rating": null,
                        "gating_info": null,
                        "id": "2626015606349461884",
                        "is_video": false,
                        "media_preview": "ACEqeIllWMMOccEfQU2VIoiF2l3bkKoGfr7Cp4jzGPT/AOINM8wQ3EjNg/cHJ9s4HHJz24oAjjClgsqNFv4BOMH2yBwT2q2toiOu0YO7+QOKLqeN1MR/iGeoyO4IHt7VM7bPLLHHUk9edtAGFvPpRWVvNFAHVRQOmxz0O38ytWXBVicZVl5HGcjpj1yP5VQuVDbWYyYCIAEbA6deh5qRYNyeXl2XIbJOWB7c+3UUASW+dmCp3M2PmGMep78Y/XipL1toBDBMBsE/QcfjSxR7GyMs3Qls9PQHp+NR3zqEG8Eg547jpz9fegDmvKHqKKk86P8Aun/P40UAX5rhozGigMXVeM9//r5H5VftWeQOrAxOCB69PT25/wDr02RFNtuIBKhcHHI6dD2q5HyoPfFAEAjuT/EBUqJLFmR28zapwMfif5VaHSnDrQByX21fSire0egooA//2Q==",
                        "shortcode": "CRxe0ffF3l8",
                        "tracking_token": "eyJ2ZXJzaW9uIjo1LCJwYXlsb2FkIjp7ImlzX2FuYWx5dGljc190cmFja2VkIjpmYWxzZSwidXVpZCI6IjQ2ZmM4MmJhMTgwNTQyODg5MmQyODQzMWNkZjY0NzE1MjYyNjAxNTYwNjM0OTQ2MTg4NCJ9LCJzaWduYXR1cmUiOiIifQ=="
                    }
                },
                {
                    "node": {
                        "__typename": "GraphImage",
                        "accessibility_caption": "Photo by Luca_bw_ on July 25, 2021. May be a black-and-white image of 1 person and outdoors.",
                        "dimensions": {
                            "height": 1350,
                            "width": 1080
                        },
                        "display_resources": [
                            {
                                "config_height": 800,
                                "config_width": 640,
                                "src": "https://instagram.fsin7-1.fna.fbcdn.net/v/t51.2885-15/sh0.08/e35/p640x640/223104494_1248266675672774_296557465844226937_n.jpg?_nc_ht=instagram.fsin7-1.fna.fbcdn.net&_nc_cat=102&_nc_ohc=_3ajFgEbV3AAX94LPE5&edm=AP_V10EBAAAA&ccb=7-4&oh=1b62d336c8bcb1126b13faead7db6877&oe=61059EE3&_nc_sid=4f375e"
                            },
                            {
                                "config_height": 937,
                                "config_width": 750,
                                "src": "https://instagram.fsin7-1.fna.fbcdn.net/v/t51.2885-15/sh0.08/e35/p750x750/223104494_1248266675672774_296557465844226937_n.jpg?_nc_ht=instagram.fsin7-1.fna.fbcdn.net&_nc_cat=102&_nc_ohc=_3ajFgEbV3AAX94LPE5&edm=AP_V10EBAAAA&ccb=7-4&oh=778f9fd26e3477e4c0a4e81b6a78a81f&oe=61045B67&_nc_sid=4f375e"
                            },
                            {
                                "config_height": 1350,
                                "config_width": 1080,
                                "src": "https://instagram.fsin7-1.fna.fbcdn.net/v/t51.2885-15/e35/p1080x1080/223104494_1248266675672774_296557465844226937_n.jpg?_nc_ht=instagram.fsin7-1.fna.fbcdn.net&_nc_cat=102&_nc_ohc=_3ajFgEbV3AAX94LPE5&edm=AP_V10EBAAAA&ccb=7-4&oh=b0f9f210878d5e40a3d581164cca68a9&oe=6105B228&_nc_sid=4f375e"
                            }
                        ],
                        "display_url": "https://instagram.fsin7-1.fna.fbcdn.net/v/t51.2885-15/e35/p1080x1080/223104494_1248266675672774_296557465844226937_n.jpg?_nc_ht=instagram.fsin7-1.fna.fbcdn.net&_nc_cat=102&_nc_ohc=_3ajFgEbV3AAX94LPE5&edm=AP_V10EBAAAA&ccb=7-4&oh=b0f9f210878d5e40a3d581164cca68a9&oe=6105B228&_nc_sid=4f375e",
                        "edge_media_to_tagged_user": {
                            "edges": []
                        },
                        "fact_check_information": null,
                        "fact_check_overall_rating": null,
                        "gating_info": null,
                        "id": "2626015606332555582",
                        "is_video": false,
                        "media_preview": "ACEqWNU2r8/QDse9OmuPs0e1CSztnI9OM/0p0SYCk9wpz+AqrfOZDtRTlSeeoI9sUAX7G88zIfqORVeRd1wxGcduB7fj+dVbSRo3+dS2eAAPw/8ArVZkw8pYdM9fyoAzKKTFFAG5IfLVP9wYz9BVIZdOhIL8jOMjGcfn+dXltVdFyx+6P5D1NRlFjDRqw69SRxwOcUAMiO0FlBVOCB268kdT+HtV2MlVUDsB6/4VTYKsTICCT0AwSfYLk5x2ojU4Hyv/AN+h/jQBn5oqLn0P/fP/ANeigDR8/CgZ7D+VTfaLbuMn3FVWH7sfQfyFR4yvPoKAL4vIB91fbpUQZF42zY+tRgAJx/nmthSc0Acr8vo9FWqKAP/Z",
                        "shortcode": "CRxe0feFYE-",
                        "tracking_token": "eyJ2ZXJzaW9uIjo1LCJwYXlsb2FkIjp7ImlzX2FuYWx5dGljc190cmFja2VkIjpmYWxzZSwidXVpZCI6IjQ2ZmM4MmJhMTgwNTQyODg5MmQyODQzMWNkZjY0NzE1MjYyNjAxNTYwNjMzMjU1NTU4MiJ9LCJzaWduYXR1cmUiOiIifQ=="
                    }
                }
            ]
        },
        "edge_web_media_to_related_media": {
            "edges": []
        },
        "fact_check_information": null,
        "fact_check_overall_rating": null,
        "gating_info": null,
        "has_ranked_comments": false,
        "id": "2626015609679574590",
        "is_ad": false,
        "is_video": false,
        "location": {
            "address_json": "{\"street_address\": \"\", \"zip_code\": \"00176\", \"city_name\": \"Rome, Italy\", \"region_name\": \"\", \"country_code\": \"IT\", \"exact_city_match\": false, \"exact_region_match\": false, \"exact_country_match\": false}",
            "has_public_page": true,
            "id": "871373479690084",
            "name": "Quartiere Pigneto",
            "slug": "quartiere-pigneto"
        },
        "media_preview": null,
        "owner": {
            "blocked_by_viewer": false,
            "followed_by_viewer": false,
            "full_name": "Luca_bw_",
            "has_blocked_viewer": false,
            "id": "7791993252",
            "is_private": false,
            "is_unpublished": false,
            "is_verified": false,
            "profile_pic_url": "https://instagram.fsin7-1.fna.fbcdn.net/v/t51.2885-19/s150x150/32247595_1687274901320478_540755486580932608_n.jpg?_nc_ht=instagram.fsin7-1.fna.fbcdn.net&_nc_ohc=QseS7evIzSEAX-qqQj9&edm=AP_V10EBAAAA&ccb=7-4&oh=1850fda9e7538ea6d46535ca8364ab26&oe=61045CFC&_nc_sid=4f375e",
            "requested_by_viewer": false,
            "username": "luca_bw_"
        },
        "shortcode": "CRxe0illPY-",
        "taken_at_timestamp": 1627265476,
        "thumbnail_resources": [
            {
                "config_height": 150,
                "config_width": 150,
                "src": "https://instagram.fsin7-1.fna.fbcdn.net/v/t51.2885-15/e35/c0.180.1440.1440a/s150x150/225063305_781609129200776_1169706515093739938_n.jpg?_nc_ht=instagram.fsin7-1.fna.fbcdn.net&_nc_cat=108&_nc_ohc=Gnfs6Ye08Y4AX8aHH-J&edm=ABZsPhsBAAAA&ccb=7-4&oh=517f8fd79997316d92d578759d7aeae0&oe=6106259B&_nc_sid=4efc9f"
            },
            {
                "config_height": 240,
                "config_width": 240,
                "src": "https://instagram.fsin7-1.fna.fbcdn.net/v/t51.2885-15/e35/c0.180.1440.1440a/s240x240/225063305_781609129200776_1169706515093739938_n.jpg?_nc_ht=instagram.fsin7-1.fna.fbcdn.net&_nc_cat=108&_nc_ohc=Gnfs6Ye08Y4AX8aHH-J&edm=ABZsPhsBAAAA&ccb=7-4&oh=5fae90dcf4d58c2083915cb15438ced3&oe=6104E09D&_nc_sid=4efc9f"
            },
            {
                "config_height": 320,
                "config_width": 320,
                "src": "https://instagram.fsin7-1.fna.fbcdn.net/v/t51.2885-15/e35/c0.180.1440.1440a/s320x320/225063305_781609129200776_1169706515093739938_n.jpg?_nc_ht=instagram.fsin7-1.fna.fbcdn.net&_nc_cat=108&_nc_ohc=Gnfs6Ye08Y4AX8aHH-J&edm=ABZsPhsBAAAA&ccb=7-4&oh=3ff0b5a854cbe69ae99f2027fbeca5ed&oe=61048EA3&_nc_sid=4efc9f"
            },
            {
                "config_height": 480,
                "config_width": 480,
                "src": "https://instagram.fsin7-1.fna.fbcdn.net/v/t51.2885-15/e35/c0.180.1440.1440a/s480x480/225063305_781609129200776_1169706515093739938_n.jpg?_nc_ht=instagram.fsin7-1.fna.fbcdn.net&_nc_cat=108&_nc_ohc=Gnfs6Ye08Y4AX8aHH-J&edm=ABZsPhsBAAAA&ccb=7-4&oh=dd8c49186193ee50e42c766bc58fa9a7&oe=6105C566&_nc_sid=4efc9f"
            },
            {
                "config_height": 640,
                "config_width": 640,
                "src": "https://instagram.fsin7-1.fna.fbcdn.net/v/t51.2885-15/sh0.08/e35/c0.180.1440.1440a/s640x640/225063305_781609129200776_1169706515093739938_n.jpg?_nc_ht=instagram.fsin7-1.fna.fbcdn.net&_nc_cat=108&_nc_ohc=Gnfs6Ye08Y4AX8aHH-J&edm=ABZsPhsBAAAA&ccb=7-4&oh=a6f6240d91bf60fc0e88d562160180a0&oe=6104982B&_nc_sid=4efc9f"
            }
        ],
        "thumbnail_src": "https://instagram.fsin7-1.fna.fbcdn.net/v/t51.2885-15/sh0.08/e35/c0.180.1440.1440a/s640x640/225063305_781609129200776_1169706515093739938_n.jpg?_nc_ht=instagram.fsin7-1.fna.fbcdn.net&_nc_cat=108&_nc_ohc=Gnfs6Ye08Y4AX8aHH-J&edm=ABZsPhsBAAAA&ccb=7-4&oh=a6f6240d91bf60fc0e88d562160180a0&oe=6104982B&_nc_sid=4efc9f",
        "tracking_token": "eyJ2ZXJzaW9uIjo1LCJwYXlsb2FkIjp7ImlzX2FuYWx5dGljc190cmFja2VkIjpmYWxzZSwidXVpZCI6IjQ2ZmM4MmJhMTgwNTQyODg5MmQyODQzMWNkZjY0NzE1MjYyNjAxNTYwOTY3OTU3NDU5MCJ9LCJzaWduYXR1cmUiOiIifQ==",
        "viewer_can_reshare": true,
        "viewer_has_liked": false,
        "viewer_has_saved": false,
        "viewer_has_saved_to_collection": false,
        "viewer_in_photo_of_you": false
    }
}